duckdb_cursor/__init__.py
duckdb_cursor/cursor.py
duckdb_cursor-0.2.dist-info/LICENSE
duckdb_cursor-0.2.dist-info/METADATA
duckdb_cursor-0.2.dist-info/WHEEL
duckdb_cursor-0.2.dist-info/top_level.txt
duckdb_cursor-0.2.dist-info/RECORD
