Metadata-Version: 2.1
Name: duckdb-cursor
Version: 0.2
Summary: DuckDB cursor wrapper
Home-page: https://gitlab.com/wcorrales/duckdb-cursor
Author: Wagner Corrales
Author-email: wagnerc4@gmail.com
License: GNU
Classifier: Development Status :: 5 - Production/Stable
Classifier: Environment :: Web Environment
Classifier: Intended Audience :: Developers
Classifier: License :: OSI Approved :: GNU General Public License v3 (GPLv3)
Classifier: Operating System :: OS Independent
Classifier: Programming Language :: Python
Classifier: Programming Language :: Python :: 3
Classifier: Programming Language :: Python :: 3.9
Classifier: Topic :: Internet :: WWW/HTTP :: Dynamic Content
Classifier: Topic :: Software Development :: Libraries :: Python Modules
Requires-Python: >=3.9
License-File: LICENSE
Requires-Dist: duckdb
